nanovicky/__init__.py
nanovicky/components/__init__.py
nanovicky/components/base_component.py
nanovicky/components/capture/__init__.py
nanovicky/components/capture/axis_camera.py
nanovicky/components/capture/base_capture_component.py
nanovicky/components/capture/camera.py
nanovicky/components/capture/cameras/__init__.py
nanovicky/components/capture/cameras/models/__init__.py
nanovicky/components/capture/cameras/models/camera.py
nanovicky/components/capture/cameras/raspi_camera_component.py
nanovicky/components/capture/cameras/usb_camera_component.py
nanovicky/components/capture/recorder.py
nanovicky/components/capture/usb_camera.py
nanovicky/components/capture/video.py
nanovicky/components/component.py
nanovicky/components/data/__init__.py
nanovicky/components/data/data_manager.py
nanovicky/components/data/gender_age_eval_file.py
nanovicky/components/data/line_crossing.py
nanovicky/components/detection/__init__.py
nanovicky/components/detection/base_detector.py
nanovicky/components/detection/caffe_detector.py
nanovicky/components/detection/edgetpu/__init__.py
nanovicky/components/detection/edgetpu/coral_dev_detector.py
nanovicky/components/detection/edgetpu/helper/__init__.py
nanovicky/components/detection/edgetpu/helper/edgetpumodel.py
nanovicky/components/detection/edgetpu/helper/nms.py
nanovicky/components/detection/edgetpu/helper/utils.py
nanovicky/components/detection/edgetpu/yolo_edgetpu_detector.py
nanovicky/components/detection/haarcascade_detector.py
nanovicky/components/detection/onnx_detector.py
nanovicky/components/detection/tflite_detector.py
nanovicky/components/detection/yolov5_detector.py
nanovicky/components/performance/__init__.py
nanovicky/components/performance/benchmark.py
nanovicky/components/performance/scheduler.py
nanovicky/components/streamer/__init__.py
nanovicky/components/streamer/displayer.py
nanovicky/components/streamer/webstreamer.py
nanovicky/components/thread_component.py
nanovicky/components/tracking/__init__.py
nanovicky-0.1.1.dist-info/METADATA
nanovicky-0.1.1.dist-info/WHEEL
nanovicky-0.1.1.dist-info/RECORD
